AxeLibrary/__init__.py
AxeLibrary/axe.py
AxeLibrary/version.py
robotframework_axelibrary-0.1.5.dist-info/LICENSE
robotframework_axelibrary-0.1.5.dist-info/METADATA
robotframework_axelibrary-0.1.5.dist-info/WHEEL
robotframework_axelibrary-0.1.5.dist-info/top_level.txt
robotframework_axelibrary-0.1.5.dist-info/RECORD
